Metadata-Version: 2.1
Name: egen112312321321213213-ibdfiu9hdfudfuy8gby
Version: 1.0
Summary: Мій проєкт
Author: Kirill
Author-email: 123@gmail.com
